rprob/__init__.py
rprob/rprob.py
rprob-1.0.4.dist-info/LICENSE
rprob-1.0.4.dist-info/METADATA
rprob-1.0.4.dist-info/WHEEL
rprob-1.0.4.dist-info/top_level.txt
rprob-1.0.4.dist-info/RECORD
