Metadata-Version: 2.1
Name: rprob
Version: 1.0.4
Summary: A library to use R style probability distribution functions in Python
Home-page: https://github.com/jinwook-chang/rprob
Author: Jinwook Chang
Author-email: Jinwook Chang <tranquil_morningl@icloud.com>
License: MIT License
Requires-Python: >=3.8
License-File: LICENSE
Requires-Dist: numpy
Requires-Dist: scipy
